tkcolorpicker/__init__.py
tkcolorpicker/__main__.py
tkcolorpicker/alphabar.py
tkcolorpicker/colorpicker.py
tkcolorpicker/colorsquare.py
tkcolorpicker/functions.py
tkcolorpicker/gradientbar.py
tkcolorpicker/limitvar.py
tkcolorpicker/spinbox.py
tkcolorpicker-2.1.3.dist-info/LICENSE.txt
tkcolorpicker-2.1.3.dist-info/METADATA
tkcolorpicker-2.1.3.dist-info/WHEEL
tkcolorpicker-2.1.3.dist-info/top_level.txt
tkcolorpicker-2.1.3.dist-info/RECORD
