Metadata-Version: 2.1
Name: tkcolorpicker
Version: 2.1.3
Summary: Color picker dialog for Tkinter
Home-page: https://github.com/j4321/tkColorPicker
Author: Juliette Monsel
Author-email: j_4321@protonmail.com
License: GPLv3
Keywords: tkinter,color,colorchooser
Platform: UNKNOWN
Classifier: Development Status :: 5 - Production/Stable
Classifier: Intended Audience :: Developers
Classifier: Topic :: Software Development :: Widget Sets
Classifier: Topic :: Software Development :: Libraries :: Python Modules
Classifier: License :: OSI Approved :: GNU General Public License v3 (GPLv3)
Classifier: Programming Language :: Python :: 3
Classifier: Programming Language :: Python :: 3.4
Classifier: Programming Language :: Python :: 3.5
Classifier: Programming Language :: Python :: 3.6
Classifier: Programming Language :: Python :: 2.7
Classifier: Natural Language :: English
Classifier: Natural Language :: French
Classifier: Operating System :: OS Independent
Requires-Dist: Pillow
